minghu6/__init__.py
minghu6/algs/__init__.py
minghu6/algs/const.py
minghu6/algs/decorator.py
minghu6/algs/dict.py
minghu6/algs/metaclass.py
minghu6/algs/ordered_set.py
minghu6/algs/pprint.py
minghu6/algs/queue.py
minghu6/algs/timeme.py
minghu6/algs/var.py
minghu6/etc/__init__.py
minghu6/etc/classtools.py
minghu6/etc/cmd.py
minghu6/etc/echo.py
minghu6/etc/fileformat.py
minghu6/etc/find.py
minghu6/etc/importer.py
minghu6/etc/launchmods.py
minghu6/etc/path.py
minghu6/etc/version.py
minghu6/etc/wraplines.py
minghu6/graphic/__init__.py
minghu6/graphic/draw_mandelbrot.py
minghu6/graphic/captcha/__init__.py
minghu6/graphic/captcha/get_image.py
minghu6/graphic/captcha/preprocessing.py
minghu6/graphic/captcha/recognise.py
minghu6/graphic/captcha/train.py
minghu6/graphic/captcha/url_captcha.py
minghu6/gui/__init__.py
minghu6/gui/appearance.py
minghu6/gui/find_key_name_of_tkinter.py
minghu6/gui/formrows.py
minghu6/gui/guimaker.py
minghu6/gui/scrolledlist.py
minghu6/gui/textConfig.py
minghu6/gui/textEditor.py
minghu6/gui/threadtools.py
minghu6/gui/windows-test.py
minghu6/gui/windows.py
minghu6/gui/TkUtil/About.py
minghu6/gui/TkUtil/Dialog.py
minghu6/gui/TkUtil/Dock.py
minghu6/gui/TkUtil/DockManager.py
minghu6/gui/TkUtil/ListBox.py
minghu6/gui/TkUtil/Scrollbar.py
minghu6/gui/TkUtil/Settings.py
minghu6/gui/TkUtil/TextEdit.py
minghu6/gui/TkUtil/Tooltip.py
minghu6/gui/TkUtil/TreeView.py
minghu6/gui/TkUtil/__init__.py
minghu6/http/__init__.py
minghu6/http/html2text.py
minghu6/http/request.py
minghu6/http/urlretrieve.py
minghu6/internet/__init__.py
minghu6/internet/mailconfig.py
minghu6/internet/proxy_ip.py
minghu6/internet/simulate_logon.py
minghu6/internet/email_self/__init__.py
minghu6/internet/email_self/mailFetcher.py
minghu6/internet/email_self/mailParser.py
minghu6/internet/email_self/mailSender.py
minghu6/internet/email_self/mailTool.py
minghu6/internet/email_self/selftest.py
minghu6/io/__init__.py
minghu6-1.1.0.dist-info/DESCRIPTION.rst
minghu6-1.1.0.dist-info/METADATA
minghu6-1.1.0.dist-info/RECORD
minghu6-1.1.0.dist-info/WHEEL
minghu6-1.1.0.dist-info/metadata.json
minghu6-1.1.0.dist-info/top_level.txt
