Metadata-Version: 2.0
Name: minghu6
Version: 1.1.0
Summary: A Core Utils Set for minghu6.
Home-page: https://github.com/minghu6/minghu6_py
Author: minghu6
Author-email: a19678zy@163.com
License: BSD License
Platform: UNKNOWN
Classifier: Intended Audience :: Developers
Classifier: License :: OSI Approved :: BSD License
Classifier: Operating System :: OS Independent
Classifier: Programming Language :: Python
Classifier: Programming Language :: Python :: 3
Classifier: Programming Language :: Python :: 3.4
Classifier: Programming Language :: Python :: 3.5
Requires-Dist: beautifulsoup4
Requires-Dist: matplotlib (>=1.5.1)
Requires-Dist: mpi4py (>=2.0.0)
Requires-Dist: numpy (>=1.11.0)
Requires-Dist: pillow
Requires-Dist: wheel
